{
  "session_id": "educational-srcbooks-2026-01-14",
  "started_at": "2026-01-14T00:00:00Z",
  "target_folder": ".specs/educational-srcbooks/",
  "phase": 6,
  "budget_total": 100,
  "budget_remaining": 1,
  "commitment_level": 100,
  "queue": [
    {
      "id": "01-cell-execution",
      "name": "Cell Execution",
      "spec_file": "01-cell-execution.md",
      "output_file": "cell-execution.src.md",
      "type": "FUNCTIONAL",
      "priority": "P0",
      "status": "DONE",
      "dependencies": [],
      "budget_allocated": 8,
      "budget_spent": 8,
      "complexity": "medium",
      "requirements_count": 12,
      "iterations": 1,
      "max_iterations": 3
    },
    {
      "id": "02-process-management",
      "name": "Process Management",
      "spec_file": "02-process-management.md",
      "output_file": "process-management.src.md",
      "type": "FUNCTIONAL",
      "priority": "P0",
      "status": "DONE",
      "dependencies": ["01-cell-execution"],
      "budget_allocated": 8,
      "budget_spent": 8,
      "complexity": "medium",
      "requirements_count": 8,
      "iterations": 1,
      "max_iterations": 3
    },
    {
      "id": "03-websocket-protocol",
      "name": "WebSocket Protocol",
      "spec_file": "03-websocket-protocol.md",
      "output_file": "websocket-protocol.src.md",
      "type": "TECHNICAL",
      "priority": "P1",
      "status": "DONE",
      "dependencies": [],
      "budget_allocated": 8,
      "budget_spent": 8,
      "complexity": "medium",
      "requirements_count": 15,
      "iterations": 1,
      "max_iterations": 3
    },
    {
      "id": "04-channels-topics",
      "name": "Channels & Topics",
      "spec_file": "04-channels-topics.md",
      "output_file": "channels-topics.src.md",
      "type": "TECHNICAL",
      "priority": "P1",
      "status": "DONE",
      "dependencies": ["03-websocket-protocol"],
      "budget_allocated": 6,
      "budget_spent": 6,
      "complexity": "low",
      "requirements_count": 10,
      "iterations": 1,
      "max_iterations": 3
    },
    {
      "id": "05-typescript-server",
      "name": "TypeScript Server",
      "spec_file": "05-typescript-server.md",
      "output_file": "typescript-server.src.md",
      "type": "FUNCTIONAL",
      "priority": "P1",
      "status": "DONE",
      "dependencies": ["01-cell-execution"],
      "budget_allocated": 10,
      "budget_spent": 10,
      "complexity": "high",
      "requirements_count": 14,
      "iterations": 1,
      "max_iterations": 3
    },
    {
      "id": "06-typescript-diagnostics",
      "name": "TypeScript Diagnostics",
      "spec_file": "06-typescript-diagnostics.md",
      "output_file": "typescript-diagnostics.src.md",
      "type": "FUNCTIONAL",
      "priority": "P1",
      "status": "DONE",
      "dependencies": ["05-typescript-server"],
      "budget_allocated": 7,
      "budget_spent": 7,
      "complexity": "medium",
      "requirements_count": 9,
      "iterations": 1,
      "max_iterations": 3
    },
    {
      "id": "07-typescript-autocomplete",
      "name": "TypeScript Autocomplete",
      "spec_file": "07-typescript-autocomplete.md",
      "output_file": "typescript-autocomplete.src.md",
      "type": "FUNCTIONAL",
      "priority": "P2",
      "status": "DONE",
      "dependencies": ["06-typescript-diagnostics"],
      "budget_allocated": 7,
      "budget_spent": 7,
      "complexity": "medium",
      "requirements_count": 8,
      "iterations": 1,
      "max_iterations": 3
    },
    {
      "id": "08-ai-integration",
      "name": "AI Integration",
      "spec_file": "08-ai-integration.md",
      "output_file": "ai-integration.src.md",
      "type": "FUNCTIONAL",
      "priority": "P1",
      "status": "DONE",
      "dependencies": ["01-cell-execution"],
      "budget_allocated": 8,
      "budget_spent": 8,
      "complexity": "medium",
      "requirements_count": 11,
      "iterations": 1,
      "max_iterations": 3
    },
    {
      "id": "09-code-generation",
      "name": "Code Generation",
      "spec_file": "09-code-generation.md",
      "output_file": "code-generation.src.md",
      "type": "FUNCTIONAL",
      "priority": "P1",
      "status": "DONE",
      "dependencies": ["08-ai-integration"],
      "budget_allocated": 8,
      "budget_spent": 8,
      "complexity": "medium",
      "requirements_count": 10,
      "iterations": 1,
      "max_iterations": 3
    },
    {
      "id": "10-ai-diagnostics-fixing",
      "name": "AI Diagnostics Fixing",
      "spec_file": "10-ai-diagnostics-fixing.md",
      "output_file": "ai-diagnostics-fixing.src.md",
      "type": "FUNCTIONAL",
      "priority": "P2",
      "status": "DONE",
      "dependencies": ["09-code-generation", "06-typescript-diagnostics"],
      "budget_allocated": 7,
      "budget_spent": 7,
      "complexity": "medium",
      "requirements_count": 7,
      "iterations": 1,
      "max_iterations": 3
    },
    {
      "id": "11-app-builder",
      "name": "App Builder",
      "spec_file": "11-app-builder.md",
      "output_file": "app-builder.src.md",
      "type": "FUNCTIONAL",
      "priority": "P2",
      "status": "DONE",
      "dependencies": [],
      "budget_allocated": 9,
      "budget_spent": 9,
      "complexity": "high",
      "requirements_count": 12,
      "iterations": 1,
      "max_iterations": 3
    },
    {
      "id": "12-database-layer",
      "name": "Database Layer",
      "spec_file": "12-database-layer.md",
      "output_file": "database-layer.src.md",
      "type": "TECHNICAL",
      "priority": "P2",
      "status": "DONE",
      "dependencies": [],
      "budget_allocated": 6,
      "budget_spent": 6,
      "complexity": "low",
      "requirements_count": 9,
      "iterations": 1,
      "max_iterations": 3
    },
    {
      "id": "13-mcp-integration",
      "name": "MCP Integration",
      "spec_file": "13-mcp-integration.md",
      "output_file": "mcp-integration.src.md",
      "type": "TECHNICAL",
      "priority": "P2",
      "status": "DONE",
      "dependencies": ["03-websocket-protocol"],
      "budget_allocated": 8,
      "budget_spent": 8,
      "complexity": "high",
      "requirements_count": 18,
      "iterations": 1,
      "max_iterations": 3
    }
  ],
  "completed": [
    "01-cell-execution",
    "03-websocket-protocol",
    "11-app-builder",
    "12-database-layer",
    "02-process-management",
    "05-typescript-server",
    "08-ai-integration",
    "04-channels-topics",
    "13-mcp-integration",
    "06-typescript-diagnostics",
    "09-code-generation",
    "07-typescript-autocomplete",
    "10-ai-diagnostics-fixing"
  ],
  "current": null,
  "signals": {
    "files_modified_history": [],
    "checklist_progress_history": [],
    "time_spent_history": []
  },
  "spiral_detection": {
    "oscillation_count": 0,
    "scope_creep_count": 0,
    "diminishing_returns_count": 0
  },
  "validation_report": ".spec-validator/educational-srcbooks-report.md",
  "recommendations_applied": [
    "Update ai-integration spec with 6 providers",
    "Add security notes to cell-execution spec"
  ]
}
